windmill/__init__.py
windmill/__main__.py
windmill/cli/__init__.py
windmill/cli/cli.py
windmill/config/__init__.py
windmill/config/project_config.py
windmill/config/run_config.py
windmill/constants.py
windmill/exceptions.py
windmill/http/__init__.py
windmill/http/api/__init__.py
windmill/http/api/endpoints.py
windmill/http/app/.gitignore
windmill/http/app/dist/.gitkeep
windmill/http/app/dist/App.40f70a3e.js
windmill/http/app/dist/App.40f70a3e.js.map
windmill/http/app/dist/favicon.ea4855f9.ico
windmill/http/app/dist/index.html
windmill/models/__init__.py
windmill/models/dags/__init__.py
windmill/models/dags/dag_handler.py
windmill/models/operators/__init__.py
windmill/models/operators/operator_handler.py
windmill/models/operators/operator_index.py
windmill/models/schemas/__init__.py
windmill/models/schemas/app_schemas.py
windmill/tasks/__init__.py
windmill/tasks/init.py
windmill/tasks/run.py
windmill/templates/dag.j2
windmill/utils/__init__.py
windmill/utils/class_parser.py
airflow_windmill-0.0.4.dist-info/entry_points.txt
airflow_windmill-0.0.4.dist-info/LICENSE
airflow_windmill-0.0.4.dist-info/WHEEL
airflow_windmill-0.0.4.dist-info/METADATA
airflow_windmill-0.0.4.dist-info/RECORD
