Metadata-Version: 2.1
Name: airflow-windmill
Version: 0.0.4
Summary: Drag'N'Drop Web Frontend for Building and Managing Airflow DAGs
Home-page: https://github.com/mayansalama/windmill
License: Apache-2.0
Author: mayansalama
Author-email: micsalama@gmail.com
Requires-Python: >=3.6,<4.0
Classifier: License :: OSI Approved :: Apache Software License
Classifier: Programming Language :: Python :: 3
Classifier: Programming Language :: Python :: 3.6
Classifier: Programming Language :: Python :: 3.7
Classifier: Programming Language :: Python :: 3.8
Provides-Extra: airflow
Requires-Dist: apache-airflow (==1.10.4); extra == "airflow"
Requires-Dist: black (>=18.3-alpha.0,<19.0)
Requires-Dist: decli (>=0.5.1,<0.6.0)
Requires-Dist: doc-cli (>=0.0.4,<0.0.5)
Requires-Dist: docstring-parser (>=0.3.0,<0.4.0)
Requires-Dist: flask-cors (>=3.0.8,<4.0.0)
Requires-Dist: gitpython (>=3.0.2,<4.0.0)
Requires-Dist: inflection (>=0.3.1,<0.4.0)
Requires-Dist: jinja2 (>=2.10.1,<3.0.0)
Requires-Dist: marshmallow (>=3.0,<4.0)
Requires-Dist: networkx (>=2.3,<3.0)
Requires-Dist: pyyaml (>=5.1.2,<6.0.0)
Project-URL: Repository, https://github.com/mayansalama/windmill
